Workbook

Sheet 1_Данные_BDU
A1: УБИ_ID | B1: Наименование угрозы | C1: Описание (кратко) | D1: Источник нарушителя (внешн/внутр) | E1: Потенциал нарушителя (Н/С/В) | F1: Объект атаки | G1: Вектор атаки (сетевой/локальный/физич.) | H1: Источник угрозы (внутр./внешн./смешанный) | I1: К | J1: Ц | K1: Д | L1: Объект воздействия (текст/перечень)
A2: 1 | B2: Угроза автоматического распространения вредоносного кода в грид-системе | C2: Угроза заключается в возможности внедрения и запуска вредоносного кода от имени доверенного процесса на любом из ресурсных центров грид-системы и его автоматического распространения на все узлы грид-системы. _x000D_ Данная угроза обусловлена слабостями технологии грид-вычислений – высоким уровнем автоматизации при малой администрируемости грид-системы._x000D_ Реализация данной угрозы возможна при условии наличия у нарушителя привилегий легального пользователя грид-системы | D2: Внешний нарушитель со средним потенциалом; Внутренний нарушитель со средним потенциалом | E2: С | F2: Ресурсные центры грид-системы | G2: локальный | H2: смешанный | I2: 1 | J2: 1 | K2: 1 | L2: перечень
A3: 2 | B3: Угроза агрегирования данных, передаваемых в грид-системе | C3: Угроза заключается в возможности раскрытия нарушителем защищаемой информации путём выявления задействованных в её обработке узлов, сбора, анализа и обобщения данных, перехватываемых в сети передачи данных грид-системы._x000D_ Данная угроза обусловлена слабостью технологии грид-вычислений – использованием незащищённых каналов сети Интернет как транспортной сети грид-системы._x000D_ Реализация данной угрозы возможна при условии наличия у нарушителя:_x000D_ сил и средств, достаточных для компенсации чрезвычайной распределённости грид-заданий между узлами грид-системы;_x000D_ привилегий, достаточных для перехвата трафика сети передачи данных между элементами (узлами) грид-системы | D3: Внешний нарушитель со средним потенциалом | E3: С | F3: Сетевой трафик | G3: сетевой | H3: внешний | I3: 1 | J3: 0 | K3: 0 | L3: перечень
A4: 3 | B4: Угроза использования слабостей криптографических алгоритмов и уязвимостей в программном обеспечении их реализации | C4: Угроза заключается в возможности выявления слабых мест в криптографических алгоритмах или уязвимостей в реализующем их программном обеспечении._x000D_ Данная угроза обусловлена слабостями криптографических алгоритмов, а также ошибками в программном коде криптографических средств, их сопряжении с системой или параметрах их настройки._x000D_ Реализация угрозы возможна в случае наличия у нарушителя сведений об применяемых в системе средствах шифрования, реализованных в них алгоритмах шифрования и параметрах их настройки | D4: Внешний нарушитель со средним потенциалом; Внутренний нарушитель со средним потенциалом | E4: С | F4: Метаданные, системное программное обеспечение | G4: локальный | H4: смешанный | I4: 1 | J4: 1 | K4: 0 | L4: перечень
A5: 4 | B5: Угроза аппаратного сброса пароля BIOS | C5: Угроза заключается в возможности сброса паролей, установленных в BIOS/UEFI без прохождения процедуры авторизации в системе путём обесточивания микросхемы BIOS (съёма аккумулятора) или установки перемычки в штатном месте на системной плате (переключение «джампера»)._x000D_ Данная угроза обусловлена уязвимостями некоторых системных (материнских) плат – наличием механизмов аппаратного сброса паролей, установленных в BIOS/UEFI._x000D_ Реализация данной угрозы возможна при условии наличия у нарушителя физического доступа к системному блоку компьютера | D5: Внутренний нарушитель с низким потенциалом | E5: Н | F5: Микропрограммное и аппаратное обеспечение BIOS/UEFI | G5: физический | H5: внутренний | I5: 0 | J5: 1 | K5: 0 | L5: перечень
A6: 5 | B6: Угроза внедрения вредоносного кода в BIOS | C6: Угроза заключается в возможности заставить BIOS/UEFI выполнять вредоносный код при каждом запуске компьютера, внедрив его в BIOS/UEFI путём замены микросхемы BIOS/UEFI или обновления программного обеспечения BIOS/UEFI на версию, уже содержащую вредоносный код._x000D_ Данная угроза обусловлена слабостями технологий контроля за обновлением программного обеспечения BIOS/UEFI и заменой чипсета BIOS/UEFI._x000D_ Реализация данной угрозы возможна в ходе проведения ремонта и обслуживания компьютера | D6: Внутренний нарушитель с высоким потенциалом | E6: В | F6: Микропрограммное и аппаратное обеспечение BIOS/UEFI | G6: сетевой | H6: внутренний | I6: 1 | J6: 1 | K6: 1 | L6: перечень
A7: 6 | B7: Угроза внедрения кода или данных | C7: Угроза заключается в возможности внедрения нарушителем в дискредитируемую информационную систему или IoT-устройство вредоносного кода, который может быть в дальнейшем запущен «вручную» пользователями, автоматически при выполнении определённого условия (наступления определённой даты, входа пользователя в систему и т.п.) или с использованием аутентификационных данных, заданных «по умолчанию», а также в возможности несанкционированного внедрения нарушителем некоторых собственных данных для обработки в дискредитируемую информационную систему, фактически осуществив незаконное использование чужих вычислительных ресурсов, и блокирования работы устройства при выполнении определенных команд._x000D_ Данная угроза обусловлена:_x000D_ наличием уязвимостей программного обеспечения;_x000D_ слабостями мер антивирусной защиты и разграничения доступа;_x000D_ наличием открытого Telnet-порта на IoT-устройстве (только для IoT-устройств)._x000D_ Реализация данной угрозы возможна:_x000D_ в случае работы дискредитируемого пользователя с файлами, поступающими из недоверенных источников;_x000D_ при наличии у него привилегий установки программного обеспечения;_x000D_ в случае неизмененных владельцем учетных данных IoT-устройства (заводских пароля и логина) | D7: Внешний нарушитель с низким потенциалом | E7: Н | F7: Системное программное обеспечение, прикладное программное обеспечение, сетевое программное обеспечение | G7: физический | H7: внешний | I7: 1 | J7: 1 | K7: 1 | L7: перечень
A8: 7 | B8: Угроза воздействия на программы с высокими привилегиями | C8: Угроза заключается в возможности повышения нарушителем своих привилегий в дискредитированной системе (получения привилегии дискредитированных программ) путём использования ошибок в программах и выполнения произвольного кода с их привилегиями._x000D_ Данная угроза обусловлена слабостями механизма проверки входных данных и команд, а также мер по разграничению доступа._x000D_ Реализация данной угрозы возможна при условиях:_x000D_ обладания дискредитируемой программой повышенными привилегиями в системе;_x000D_ осуществления дискредитируемой программой приёма входных данных от других программ или от пользователя;_x000D_ нарушитель имеет возможность осуществлять передачу данных к дискредитируемой программе | D8: Внешний нарушитель со средним потенциалом; Внутренний нарушитель со средним потенциалом | E8: С | F8: Информационная система, виртуальная машина, сетевое программное обеспечение, сетевой трафик | G8: локальный | H8: смешанный | I8: 1 | J8: 1 | K8: 0 | L8: перечень
A9: 8 | B9: Угроза восстановления и/или повторного использования аутентификационной информации | C9: Угроза заключается в возможности доступа к данным пользователя в результате подбора (например, путём полного перебора или перебора по словарю) аутентификационной информации дискредитируемой учётной записи пользователя в системе, а также путём перехвата и повторного использования хэша пароля, для восстановления сеанса._x000D_ Данная угроза обусловлена следующими недостатками:_x000D_ значительно меньшим объёмом данных хеш-кода аутентификационной информации по сравнению с ней самой (время подбора хеш-кодов меньше времени полного перебора аутентификационной информации); _x000D_ слабостями алгоритма расчёта хеш-кода, допускающими его повторное использование для выполнения успешной аутентификации._x000D_ Реализация данной угрозы возможна с помощью специальных программных средств, а также в некоторых случаях – «вручную» | D9: Внешний нарушитель с низким потенциалом; Внутренний нарушитель с низким потенциалом | E9: Н | F9: Системное программное обеспечение, микропрограммное обеспечение, учётные данные пользователя | G9: локальный | H9: смешанный | I9: 1 | J9: 0 | K9: 0 | L9: перечень
A10: 9 | B10: Угроза восстановления предыдущей уязвимой версии BIOS | C10: Угроза заключается в возможности осуществления вынужденного перехода на использование BIOS/UEFI, содержащей уязвимости._x000D_ Данная угроза обусловлена слабостями технологий контроля за обновлением программного обеспечения BIOS/UEFI._x000D_ При использовании технологии обновления BIOS/UEFI возможно возникновение следующей ситуации (условия, характеризующие ситуацию указаны в хронологическом порядке): _x000D_ на компьютере установлена некоторая версия BIOS/UEFI, для которой на момент её работы не известны уязвимости; _x000D_ в силу некоторых обстоятельств BIOS/UEFI проходит процедуру обновления, сохраняя при этом предыдущую версию BIOS/UEFI на случай «отката» системы; _x000D_ публикуются данные о существовании уязвимостей в предыдущей версии BIOS/UEFI; _x000D_ происходит сбой в работе системы, в результате чего текущая (новая) версия BIOS/UEFI становится неработоспособной (например, нарушается её целостность);_x000D_ пользователь осуществляет штатную процедуру восстановления работоспособности системы – проводит «откат» системы к предыдущему работоспособному состоянию | D10: Внутренний нарушитель с низким потенциалом | E10: Н | F10: Микропрограммное обеспечение BIOS/UEFI | G10: локальный | H10: внутренний | I10: 1 | J10: 1 | K10: 1 | L10: перечень
A11: 10 | B11: Угроза выхода процесса за пределы виртуальной машины | C11: Угроза заключается в возможности запуска вредоносной программой собственного гипервизора, функционирующего по уровню логического взаимодействия ниже компрометируемого гипервизора._x000D_ Данная угроза обусловлена уязвимостями программного обеспечения гипервизора, реализующего функцию изолированной программной среды для функционирующих в ней программ, а также слабостями инструкций аппаратной поддержки виртуализации на уровне процессора._x000D_ Реализация данной угрозы приводит не только к компрометации гипервизора, но и запущенных в созданной им виртуальной среде средств защиты, а, следовательно, к их неспособности выполнять функции безопасности в отношении вредоносных программ, функционирующих под управлением собственного гипервизора | D11: Внешний нарушитель со средним потенциалом; Внутренний нарушитель со средним потенциалом | E11: С | F11: Информационная система, сетевой узел, носитель информации, объекты файловой системы, учётные данные пользователя, образ виртуальной машины | G11: локальный | H11: смешанный | I11: 1 | J11: 1 | K11: 1 | L11: перечень
A12: 11 | B12: Угроза деавторизации санкционированного клиента беспроводной сети | C12: Угроза заключается в возможности автоматического разрыва соединения беспроводной точки доступа с санкционированным клиентом беспроводной сети._x000D_ Данная угроза обусловлена слабостью технологий сетевого взаимодействия по беспроводным каналам передачи данных – сведения о МАС-адресах беспроводных клиентов доступны всем участникам сетевого взаимодействия._x000D_ Реализация данной угрозы возможна при условии подключения нарушителем к беспроводной сети устройства, МАС-адрес которого будет полностью совпадать с МАС-адресом дискредитируемого санкционированного клиента | D12: Внешний нарушитель с низким потенциалом; Внутренний нарушитель с низким потенциалом | E12: Н | F12: Сетевой узел | G12: сетевой | H12: смешанный | I12: 0 | J12: 0 | K12: 1 | L12: перечень
A13: 12 | B13: Угроза деструктивного изменения конфигурации/среды окружения программ | C13: Угроза заключается в возможности деструктивного программного воздействия на дискредитируемое приложение путём осуществления манипуляций с используемыми им конфигурационными файлами или библиотеками._x000D_ Данная угроза обусловлена слабостями мер контроля целостности конфигурационных файлов или библиотек, используемых приложениями._x000D_ Реализация данной угрозы возможна в случае наличия у нарушителя прав осуществления записи в файловые объекты, связанные с конфигурацией/средой окружения программы, или возможности перенаправления запросов дискредитируемой программы от защищённых файловых объектов к ложным | D13: Внутренний нарушитель с низким потенциалом | E13: Н | F13: Системное программное обеспечение, прикладное программное обеспечение, сетевое программное обеспечение, микропрограммное обеспечение, метаданные, объекты файловой системы, реестр | G13: локальный | H13: внутренний | I13: 1 | J13: 1 | K13: 1 | L13: перечень
... A228: 227 | B228: Угроза модификации (подмены) образов контейнеров | C228: Угроза заключается в возможности осуществления деструктивного программного воздействия на дискредитируемую систему или опосредованного деструктивного программного воздействия через нее на другие системы путем осуществления несанкционированного доступа к образам docker-контейнеров. Данная угроза обусловлена слабостями мер разграничения доступа к образам docker-контейнеров, реализованных в программном обеспечении контейнеризации. Реализация данной угрозы может привести к нарушению конфиденциальности информации, целостности программного обеспечения и доступности ресурсов docker-контейнеров, а также создания ботнета путем внедрения вредоносного программного обеспечения в образы docker-контейнеров, используемых в качестве шаблонов. | D228: Внешний нарушитель со средним потенциалом; Внутренний нарушитель со средним потенциалом | E228: С | F228: Образ docker-контейнера, сетевой узел, сетевое программное обеспечение, docker-контейнер | G228: локальный | H228: смешанный | I228: 1 | J228: 1 | K228: 1 | L228: перечень
I229: =SUM(I2:I228) -> 150 | J229: =SUM(J2:J228) -> 142 | K229: =SUM(K2:K228) -> 160

Sheet 2_Фичи
A1: УБИ_ID | B1: C (0/1) | C1: I (0/1) | D1: A (0/1) | E1: Потенциал_балл (Н=1,С=2,В=3) | F1: Вектор_балл (сетевой=3,локал=2,физ=1,см=2.5) | G1: Источник_балл (внеш=1.2,внутр=1.1,см=1.25) | H1: Объект_сложность (log(1+число_ключевых_слов)) | I1: Фичи_норма (для кластеризации)
A2: ='1_Данные_BDU'!A2 -> 1 | B2: =IF('1_Данные_BDU'!I2="",0,VALUE('1_Данные_BDU'!I2)) -> 1 | C2: =IF('1_Данные_BDU'!J2="",0,VALUE('1_Данные_BDU'!J2)) -> 1 | D2: =IF('1_Данные_BDU'!K2="",0,VALUE('1_Данные_BDU'!K2)) -> 1 | E2: =IF('1_Данные_BDU'!E2="Н",1,IF('1_Данные_BDU'!E2="С",2,IF('1_Данные_BDU'!E2="В",3,""))) -> 2 | F2: =IF('1_Данные_BDU'!G2="сетевой",3,IF('1_Данные_BDU'!G2="локальный",2,IF('1_Данные_BDU'!G2="физический",1,IF('1_Данные_BDU'!G2="смешанный",2.5,"")))) -> 2 | G2: =IF('1_Данные_BDU'!H2="внешний",1.2,IF('1_Данные_BDU'!H2="внутренний",1.1,IF('1_Данные_BDU'!H2="смешанный",1.25,""))) -> 1.25 | H2: =IF('1_Данные_BDU'!L2="перечень",1,0) -> 1 | I2: =IF(A2="","",(2*B2+2*C2+2*D2)*E2*F2*G2*(1+H2)) -> 60
A3: ='1_Данные_BDU'!A3 -> 2 | B3: =IF('1_Данные_BDU'!I3="",0,VALUE('1_Данные_BDU'!I3)) -> 1 | C3: =IF('1_Данные_BDU'!J3="",0,VALUE('1_Данные_BDU'!J3)) -> 0 | D3: =IF('1_Данные_BDU'!K3="",0,VALUE('1_Данные_BDU'!K3)) -> 0 | E3: =IF('1_Данные_BDU'!E3="Н",1,IF('1_Данные_BDU'!E3="С",2,IF('1_Данные_BDU'!E3="В",3,""))) -> 2 | F3: =IF('1_Данные_BDU'!G3="сетевой",3,IF('1_Данные_BDU'!G3="локальный",2,IF('1_Данные_BDU'!G3="физический",1,IF('1_Данные_BDU'!G3="смешанный",2.5,"")))) -> 3 | G3: =IF('1_Данные_BDU'!H3="внешний",1.2,IF('1_Данные_BDU'!H3="внутренний",1.1,IF('1_Данные_BDU'!H3="смешанный",1.25,""))) -> 1.2 | H3: =IF('1_Данные_BDU'!L3="перечень",1,0) -> 1 | I3: =IF(A3="","",(2*B3+2*C3+2*D3)*E3*F3*G3*(1+H3)) -> 28.8
A4: ='1_Данные_BDU'!A4 -> 3 | B4: =IF('1_Данные_BDU'!I4="",0,VALUE('1_Данные_BDU'!I4)) -> 1 | C4: =IF('1_Данные_BDU'!J4="",0,VALUE('1_Данные_BDU'!J4)) -> 1 | D4: =IF('1_Данные_BDU'!K4="",0,VALUE('1_Данные_BDU'!K4)) -> 0 | E4: =IF('1_Данные_BDU'!E4="Н",1,IF('1_Данные_BDU'!E4="С",2,IF('1_Данные_BDU'!E4="В",3,""))) -> 2 | F4: =IF('1_Данные_BDU'!G4="сетевой",3,IF('1_Данные_BDU'!G4="локальный",2,IF('1_Данные_BDU'!G4="физический",1,IF('1_Данные_BDU'!G4="смешанный",2.5,"")))) -> 2 | G4: =IF('1_Данные_BDU'!H4="внешний",1.2,IF('1_Данные_BDU'!H4="внутренний",1.1,IF('1_Данные_BDU'!H4="смешанный",1.25,""))) -> 1.25 | H4: =IF('1_Данные_BDU'!L4="перечень",1,0) -> 1 | I4: =IF(A4="","",(2*B4+2*C4+2*D4)*E4*F4*G4*(1+H4)) -> 40
A5: ='1_Данные_BDU'!A5 -> 4 | B5: =IF('1_Данные_BDU'!I5="",0,VALUE('1_Данные_BDU'!I5)) -> 0 | C5: =IF('1_Данные_BDU'!J5="",0,VALUE('1_Данные_BDU'!J5)) -> 1 | D5: =IF('1_Данные_BDU'!K5="",0,VALUE('1_Данные_BDU'!K5)) -> 0 | E5: =IF('1_Данные_BDU'!E5="Н",1,IF('1_Данные_BDU'!E5="С",2,IF('1_Данные_BDU'!E5="В",3,""))) -> 1 | F5: =IF('1_Данные_BDU'!G5="сетевой",3,IF('1_Данные_BDU'!G5="локальный",2,IF('1_Данные_BDU'!G5="физический",1,IF('1_Данные_BDU'!G5="смешанный",2.5,"")))) -> 1 | G5: =IF('1_Данные_BDU'!H5="внешний",1.2,IF('1_Данные_BDU'!H5="внутренний",1.1,IF('1_Данные_BDU'!H5="смешанный",1.25,""))) -> 1.1 | H5: =IF('1_Данные_BDU'!L5="перечень",1,0) -> 1 | I5: =IF(A5="","",(2*B5+2*C5+2*D5)*E5*F5*G5*(1+H5)) -> 4.4
A6: ='1_Данные_BDU'!A6 -> 5 | B6: =IF('1_Данные_BDU'!I6="",0,VALUE('1_Данные_BDU'!I6)) -> 1 | C6: =IF('1_Данные_BDU'!J6="",0,VALUE('1_Данные_BDU'!J6)) -> 1 | D6: =IF('1_Данные_BDU'!K6="",0,VALUE('1_Данные_BDU'!K6)) -> 1 | E6: =IF('1_Данные_BDU'!E6="Н",1,IF('1_Данные_BDU'!E6="С",2,IF('1_Данные_BDU'!E6="В",3,""))) -> 3 | F6: =IF('1_Данные_BDU'!G6="сетевой",3,IF('1_Данные_BDU'!G6="локальный",2,IF('1_Данные_BDU'!G6="физический",1,IF('1_Данные_BDU'!G6="смешанный",2.5,"")))) -> 3 | G6: =IF('1_Данные_BDU'!H6="внешний",1.2,IF('1_Данные_BDU'!H6="внутренний",1.1,IF('1_Данные_BDU'!H6="смешанный",1.25,""))) -> 1.1 | H6: =IF('1_Данные_BDU'!L6="перечень",1,0) -> 1 | I6: =IF(A6="","",(2*B6+2*C6+2*D6)*E6*F6*G6*(1+H6)) -> 118.8
A7: ='1_Данные_BDU'!A7 -> 6 | B7: =IF('1_Данные_BDU'!I7="",0,VALUE('1_Данные_BDU'!I7)) -> 1 | C7: =IF('1_Данные_BDU'!J7="",0,VALUE('1_Данные_BDU'!J7)) -> 1 | D7: =IF('1_Данные_BDU'!K7="",0,VALUE('1_Данные_BDU'!K7)) -> 1 | E7: =IF('1_Данные_BDU'!E7="Н",1,IF('1_Данные_BDU'!E7="С",2,IF('1_Данные_BDU'!E7="В",3,""))) -> 1 | F7: =IF('1_Данные_BDU'!G7="сетевой",3,IF('1_Данные_BDU'!G7="локальный",2,IF('1_Данные_BDU'!G7="физический",1,IF('1_Данные_BDU'!G7="смешанный",2.5,"")))) -> 1 | G7: =IF('1_Данные_BDU'!H7="внешний",1.2,IF('1_Данные_BDU'!H7="внутренний",1.1,IF('1_Данные_BDU'!H7="смешанный",1.25,""))) -> 1.2 | H7: =IF('1_Данные_BDU'!L7="перечень",1,0) -> 1 | I7: =IF(A7="","",(2*B7+2*C7+2*D7)*E7*F7*G7*(1+H7)) -> 14.4
A8: ='1_Данные_BDU'!A8 -> 7 | B8: =IF('1_Данные_BDU'!I8="",0,VALUE('1_Данные_BDU'!I8)) -> 1 | C8: =IF('1_Данные_BDU'!J8="",0,VALUE('1_Данные_BDU'!J8)) -> 1 | D8: =IF('1_Данные_BDU'!K8="",0,VALUE('1_Данные_BDU'!K8)) -> 0 | E8: =IF('1_Данные_BDU'!E8="Н",1,IF('1_Данные_BDU'!E8="С",2,IF('1_Данные_BDU'!E8="В",3,""))) -> 2 | F8: =IF('1_Данные_BDU'!G8="сетевой",3,IF('1_Данные_BDU'!G8="локальный",2,IF('1_Данные_BDU'!G8="физический",1,IF('1_Данные_BDU'!G8="смешанный",2.5,"")))) -> 2 | G8: =IF('1_Данные_BDU'!H8="внешний",1.2,IF('1_Данные_BDU'!H8="внутренний",1.1,IF('1_Данные_BDU'!H8="смешанный",1.25,""))) -> 1.25 | H8: =IF('1_Данные_BDU'!L8="перечень",1,0) -> 1 | I8: =IF(A8="","",(2*B8+2*C8+2*D8)*E8*F8*G8*(1+H8)) -> 40
A9: ='1_Данные_BDU'!A9 -> 8 | B9: =IF('1_Данные_BDU'!I9="",0,VALUE('1_Данные_BDU'!I9)) -> 1 | C9: =IF('1_Данные_BDU'!J9="",0,VALUE('1_Данные_BDU'!J9)) -> 0 | D9: =IF('1_Данные_BDU'!K9="",0,VALUE('1_Данные_BDU'!K9)) -> 0 | E9: =IF('1_Данные_BDU'!E9="Н",1,IF('1_Данные_BDU'!E9="С",2,IF('1_Данные_BDU'!E9="В",3,""))) -> 1 | F9: =IF('1_Данные_BDU'!G9="сетевой",3,IF('1_Данные_BDU'!G9="локальный",2,IF('1_Данные_BDU'!G9="физический",1,IF('1_Данные_BDU'!G9="смешанный",2.5,"")))) -> 2 | G9: =IF('1_Данные_BDU'!H9="внешний",1.2,IF('1_Данные_BDU'!H9="внутренний",1.1,IF('1_Данные_BDU'!H9="смешанный",1.25,""))) -> 1.25 | H9: =IF('1_Данные_BDU'!L9="перечень",1,0) -> 1 | I9: =IF(A9="","",(2*B9+2*C9+2*D9)*E9*F9*G9*(1+H9)) -> 10
A10: ='1_Данные_BDU'!A10 -> 9 | B10: =IF('1_Данные_BDU'!I10="",0,VALUE('1_Данные_BDU'!I10)) -> 1 | C10: =IF('1_Данные_BDU'!J10="",0,VALUE('1_Данные_BDU'!J10)) -> 1 | D10: =IF('1_Данные_BDU'!K10="",0,VALUE('1_Данные_BDU'!K10)) -> 1 | E10: =IF('1_Данные_BDU'!E10="Н",1,IF('1_Данные_BDU'!E10="С",2,IF('1_Данные_BDU'!E10="В",3,""))) -> 1 | F10: =IF('1_Данные_BDU'!G10="сетевой",3,IF('1_Данные_BDU'!G10="локальный",2,IF('1_Данные_BDU'!G10="физический",1,IF('1_Данные_BDU'!G10="смешанный",2.5,"")))) -> 2 | G10: =IF('1_Данные_BDU'!H10="внешний",1.2,IF('1_Данные_BDU'!H10="внутренний",1.1,IF('1_Данные_BDU'!H10="смешанный",1.25,""))) -> 1.1 | H10: =IF('1_Данные_BDU'!L10="перечень",1,0) -> 1 | I10: =IF(A10="","",(2*B10+2*C10+2*D10)*E10*F10*G10*(1+H10)) -> 26.4
A11: ='1_Данные_BDU'!A11 -> 10 | B11: =IF('1_Данные_BDU'!I11="",0,VALUE('1_Данные_BDU'!I11)) -> 1 | C11: =IF('1_Данные_BDU'!J11="",0,VALUE('1_Данные_BDU'!J11)) -> 1 | D11: =IF('1_Данные_BDU'!K11="",0,VALUE('1_Данные_BDU'!K11)) -> 1 | E11: =IF('1_Данные_BDU'!E11="Н",1,IF('1_Данные_BDU'!E11="С",2,IF('1_Данные_BDU'!E11="В",3,""))) -> 2 | F11: =IF('1_Данные_BDU'!G11="сетевой",3,IF('1_Данные_BDU'!G11="локальный",2,IF('1_Данные_BDU'!G11="физический",1,IF('1_Данные_BDU'!G11="смешанный",2.5,"")))) -> 2 | G11: =IF('1_Данные_BDU'!H11="внешний",1.2,IF('1_Данные_BDU'!H11="внутренний",1.1,IF('1_Данные_BDU'!H11="смешанный",1.25,""))) -> 1.25 | H11: =IF('1_Данные_BDU'!L11="перечень",1,0) -> 1 | I11: =IF(A11="","",(2*B11+2*C11+2*D11)*E11*F11*G11*(1+H11)) -> 60
A12: ='1_Данные_BDU'!A12 -> 11 | B12: =IF('1_Данные_BDU'!I12="",0,VALUE('1_Данные_BDU'!I12)) -> 0 | C12: =IF('1_Данные_BDU'!J12="",0,VALUE('1_Данные_BDU'!J12)) -> 0 | D12: =IF('1_Данные_BDU'!K12="",0,VALUE('1_Данные_BDU'!K12)) -> 1 | E12: =IF('1_Данные_BDU'!E12="Н",1,IF('1_Данные_BDU'!E12="С",2,IF('1_Данные_BDU'!E12="В",3,""))) -> 1 | F12: =IF('1_Данные_BDU'!G12="сетевой",3,IF('1_Данные_BDU'!G12="локальный",2,IF('1_Данные_BDU'!G12="физический",1,IF('1_Данные_BDU'!G12="смешанный",2.5,"")))) -> 3 | G12: =IF('1_Данные_BDU'!H12="внешний",1.2,IF('1_Данные_BDU'!H12="внутренний",1.1,IF('1_Данные_BDU'!H12="смешанный",1.25,""))) -> 1.25 | H12: =IF('1_Данные_BDU'!L12="перечень",1,0) -> 1 | I12: =IF(A12="","",(2*B12+2*C12+2*D12)*E12*F12*G12*(1+H12)) -> 15
A13: ='1_Данные_BDU'!A13 -> 12 | B13: =IF('1_Данные_BDU'!I13="",0,VALUE('1_Данные_BDU'!I13)) -> 1 | C13: =IF('1_Данные_BDU'!J13="",0,VALUE('1_Данные_BDU'!J13)) -> 1 | D13: =IF('1_Данные_BDU'!K13="",0,VALUE('1_Данные_BDU'!K13)) -> 1 | E13: =IF('1_Данные_BDU'!E13="Н",1,IF('1_Данные_BDU'!E13="С",2,IF('1_Данные_BDU'!E13="В",3,""))) -> 1 | F13: =IF('1_Данные_BDU'!G13="сетевой",3,IF('1_Данные_BDU'!G13="локальный",2,IF('1_Данные_BDU'!G13="физический",1,IF('1_Данные_BDU'!G13="смешанный",2.5,"")))) -> 2 | G13: =IF('1_Данные_BDU'!H13="внешний",1.2,IF('1_Данные_BDU'!H13="внутренний",1.1,IF('1_Данные_BDU'!H13="смешанный",1.25,""))) -> 1.1 | H13: =IF('1_Данные_BDU'!L13="перечень",1,0) -> 1 | I13: =IF(A13="","",(2*B13+2*C13+2*D13)*E13*F13*G13*(1+H13)) -> 26.4
... A228: ='1_Данные_BDU'!A228 -> 227 | B228: =IF('1_Данные_BDU'!I228="",0,VALUE('1_Данные_BDU'!I228)) -> 1 | C228: =IF('1_Данные_BDU'!J228="",0,VALUE('1_Данные_BDU'!J228)) -> 1 | D228: =IF('1_Данные_BDU'!K228="",0,VALUE('1_Данные_BDU'!K228)) -> 1 | E228: =IF('1_Данные_BDU'!E228="Н",1,IF('1_Данные_BDU'!E228="С",2,IF('1_Данные_BDU'!E228="В",3,""))) -> 2 | F228: =IF('1_Данные_BDU'!G228="сетевой",3,IF('1_Данные_BDU'!G228="локальный",2,IF('1_Данные_BDU'!G228="физический",1,IF('1_Данные_BDU'!G228="смешанный",2.5,"")))) -> 2 | G228: =IF('1_Данные_BDU'!H228="внешний",1.2,IF('1_Данные_BDU'!H228="внутренний",1.1,IF('1_Данные_BDU'!H228="смешанный",1.25,""))) -> 1.25 | H228: =IF('1_Данные_BDU'!L228="перечень",1,0) -> 1 | I228: =IF(A228="","",(2*B228+2*C228+2*D228)*E228*F228*G228*(1+H228)) -> 60
A229: ='1_Данные_BDU'!A229 -> 0 | B229: =IF('1_Данные_BDU'!I229="",0,VALUE('1_Данные_BDU'!I229)) -> 150 | C229: =IF('1_Данные_BDU'!J229="",0,VALUE('1_Данные_BDU'!J229)) -> 142 | D229: =IF('1_Данные_BDU'!K229="",0,VALUE('1_Данные_BDU'!K229)) -> 160 | E229: =SUM(E2:E228) -> 348 | F229: =SUM(F2:F228) -> 494 | G229: =SUM(G2:G228) -> 274.45 | H229: =SUM(H2:H228) -> 225 | I229: =IF(A229="","",(2*B229+2*C229+2*D229)*E229*F229*G229*(1+H229)) -> 9.6393178e+12

Sheet 3_Метрика_Парето
A1: УБИ_ID | B1: Наименование | C1: ToxIndex (0..100) | D1: Ранг (1=самая токсичная) | E1: Доля токсичности, % | F1: Накопленная доля, % | G1: Класс CIA (C/I/A/CI/CA/IA/CIA) | H1: Кластер_9 | I1: Кластер_16 | J1: Кластер_25 | K1: Парето_ядро (80%) | L1: Контроль данных | N1: Контроль (сводка)
A2: ='2_Фичи'!A2 -> 1 | B2: ='1_Данные_BDU'!B2 -> Угроза автоматического распространения вредоносного кода в грид-системе | C2: 44.41 | D2: 13 | E2: 0.882 | F2: 17.98 | G2: CIA | H2: 1 | I2: 1 | J2: =IF($D2="","",CEILING($D2/(COUNT($D$2:$D$229)/25),1)) -> 2 | K2: =IF($F2="","",IF($F2<=80,"ДА","")) -> ДА | N2: Ошибок (не OK) | O2: =COUNTIF(L2:L229,"<>OK")-COUNTIF(L2:L229,"") -> 0
A3: ='2_Фичи'!A3 -> 2 | B3: ='1_Данные_BDU'!B3 -> Угроза агрегирования данных, передаваемых в грид-системе | C3: 19.49 | D3: 109 | E3: 0.3871 | F3: 79.14 | G3: C | H3: 5 | I3: 8 | J3: =IF($D3="","",CEILING($D3/(COUNT($D$2:$D$229)/25),1)) -> 13 | K3: =IF($F3="","",IF($F3<=80,"ДА","")) -> ДА | N3: OK | O3: =COUNTIF(L2:L229,"OK") -> 0
A4: ='2_Фичи'!A4 -> 3 | B4: ='1_Данные_BDU'!B4 -> Угроза использования слабостей криптографических алгоритмов и уязвимостей в программном обеспечении их реализации | C4: 28.43 | D4: 65 | E4: 0.5646 | F4: 59.33 | G4: CI | H4: 3 | I4: 5 | J4: =IF($D4="","",CEILING($D4/(COUNT($D$2:$D$229)/25),1)) -> 8 | K4: =IF($F4="","",IF($F4<=80,"ДА","")) -> ДА | N4: sumT | O4: =SUM(C2:C229) -> 10070.7
A5: ='2_Фичи'!A5 -> 4 | B5: ='1_Данные_BDU'!B5 -> Угроза аппаратного сброса пароля BIOS | C5: 0 | D5: 226 | E5: 0 | F5: 100 | G5: I | H5: 9 | I5: 16 | J5: =IF($D5="","",CEILING($D5/(COUNT($D$2:$D$229)/25),1)) -> 25 | K5: =IF($F5="","",IF($F5<=80,"ДА",""))
A6: ='2_Фичи'!A6 -> 5 | B6: ='1_Данные_BDU'!B6 -> Угроза внедрения вредоносного кода в BIOS | C6: 91.37 | D6: 2 | E6: 1.8146 | F6: 3.8 | G6: CIA | H6: 1 | I6: 1 | J6: =IF($D6="","",CEILING($D6/(COUNT($D$2:$D$229)/25),1)) -> 1 | K6: =IF($F6="","",IF($F6<=80,"ДА","")) -> ДА
A7: ='2_Фичи'!A7 -> 6 | B7: ='1_Данные_BDU'!B7 -> Угроза внедрения кода или данных | C7: 7.99 | D7: 168 | E7: 0.1587 | F7: 94.62 | G7: CIA | H7: 7 | I7: 12 | J7: =IF($D7="","",CEILING($D7/(COUNT($D$2:$D$229)/25),1)) -> 19 | K7: =IF($F7="","",IF($F7<=80,"ДА",""))
A8: ='2_Фичи'!A8 -> 7 | B8: ='1_Данные_BDU'!B8 -> Угроза воздействия на программы с высокими привилегиями | C8: 28.43 | D8: 66 | E8: 0.5646 | F8: 59.9 | G8: CI | H8: 3 | I8: 5 | J8: =IF($D8="","",CEILING($D8/(COUNT($D$2:$D$229)/25),1)) -> 8 | K8: =IF($F8="","",IF($F8<=80,"ДА","")) -> ДА
A9: ='2_Фичи'!A9 -> 8 | B9: ='1_Данные_BDU'!B9 -> Угроза восстановления и/или повторного использования аутентификационной информации | C9: 4.47 | D9: 184 | E9: 0.0888 | F9: 97.02 | G9: C | H9: 8 | I9: 13 | J9: =IF($D9="","",CEILING($D9/(COUNT($D$2:$D$229)/25),1)) -> 21 | K9: =IF($F9="","",IF($F9<=80,"ДА",""))
A10: ='2_Фичи'!A10 -> 9 | B10: ='1_Данные_BDU'!B10 -> Угроза восстановления предыдущей уязвимой версии BIOS | C10: 17.57 | D10: 124 | E10: 0.3489 | F10: 84.91 | G10: CIA | H10: 5 | I10: 9 | J10: =IF($D10="","",CEILING($D10/(COUNT($D$2:$D$229)/25),1)) -> 14 | K10: =IF($F10="","",IF($F10<=80,"ДА",""))
A11: ='2_Фичи'!A11 -> 10 | B11: ='1_Данные_BDU'!B11 -> Угроза выхода процесса за пределы виртуальной машины | C11: 44.41 | D11: 14 | E11: 0.882 | F11: 18.86 | G11: CIA | H11: 1 | I11: 1 | J11: =IF($D11="","",CEILING($D11/(COUNT($D$2:$D$229)/25),1)) -> 2 | K11: =IF($F11="","",IF($F11<=80,"ДА","")) -> ДА
A12: ='2_Фичи'!A12 -> 11 | B12: ='1_Данные_BDU'!B12 -> Угроза деавторизации санкционированного клиента беспроводной сети | C12: 8.47 | D12: 154 | E12: 0.1682 | F12: 92.28 | G12: A | H12: 7 | I12: 11 | J12: =IF($D12="","",CEILING($D12/(COUNT($D$2:$D$229)/25),1)) -> 17 | K12: =IF($F12="","",IF($F12<=80,"ДА",""))
A13: ='2_Фичи'!A13 -> 12 | B13: ='1_Данные_BDU'!B13 -> Угроза деструктивного изменения конфигурации/среды окружения программ | C13: 17.57 | D13: 125 | E13: 0.3489 | F13: 85.26 | G13: CIA | H13: 5 | I13: 9 | J13: =IF($D13="","",CEILING($D13/(COUNT($D$2:$D$229)/25),1)) -> 14 | K13: =IF($F13="","",IF($F13<=80,"ДА",""))
A14: ='2_Фичи'!A14 -> 13 | B14: ='1_Данные_BDU'!B14 -> Угроза деструктивного использования декларированного функционала BIOS | C14: 0.48 | D14: 221 | E14: 0.0095 | F14: 99.96 | G14: I | H14: 9 | I14: 16 | J14: =IF($D14="","",CEILING($D14/(COUNT($D$2:$D$229)/25),1)) -> 25 | K14: =IF($F14="","",IF($F14<=80,"ДА",""))
A15: ='2_Фичи'!A15 -> 14 | B15: ='1_Данные_BDU'!B15 -> Угроза длительного удержания вычислительных ресурсов пользователями | C15: 4.47 | D15: 185 | E15: 0.0888 | F15: 97.11 | G15: A | H15: 8 | I15: 14 | J15: =IF($D15="","",CEILING($D15/(COUNT($D$2:$D$229)/25),1)) -> 21 | K15: =IF($F15="","",IF($F15<=80,"ДА",""))
A16: ='2_Фичи'!A16 -> 15 | B16: ='1_Данные_BDU'!B16 -> Угроза доступа к защищаемым файлам с использованием обходного пути | C16: 4.47 | D16: 186 | E16: 0.0888 | F16: 97.19 | G16: C | H16: 8 | I16: 14 | J16: =IF($D16="","",CEILING($D16/(COUNT($D$2:$D$229)/25),1)) -> 21 | K16: =IF($F16="","",IF($F16<=80,"ДА",""))
... A228: ='2_Фичи'!A228 -> 227 | B228: ='1_Данные_BDU'!B228 -> Угроза модификации (подмены) образов контейнеров | C228: 44.41 | D228: 40 | E228: 0.882 | F228: 41.79 | G228: CIA | H228: 2 | I228: 3 | J228: =IF($D228="","",CEILING($D228/(COUNT($D$2:$D$229)/25),1)) -> 5 | K228: =IF($F228="","",IF($F228<=80,"ДА","")) -> ДА
C229: =SUM(C2:C228) -> 5035.35

Sheet 0_Как_пользоваться
A1: Инструмент объективной кластеризации 227 угроз БДУ (ФСТЭК) под 9/16/25-факторные модели бюджетирования
A3: Шаг 1. Откройте официальный файл thrlist.xlsx (БДУ ФСТЭК) и скопируйте строки с угрозами в лист '1_Данные_BDU' (начиная со строки 2).
A4: Шаг 2. Заполните/проверьте колонки: Источник, Потенциал, Вектор, флаги К/Ц/Д (0/1). Если эти поля есть в выгрузке — просто сопоставьте столбцы.
A5: Шаг 3. Листы '2_Фичи' и '3_Метрика_Парето' автоматически вычислят:
A6: • ToxIndex — объективный индекс «ядовитости» на основе структуры данных (CIA × потенциал × вектор × источник × сложность объекта воздействия).
A7: • Ранги, долю и накопленную долю — для правила Парето (ядро 80%).
A8: • Кластеры 9/16/25 — автоматически по квантилям (без экспертных «ручных» оценок).
A10: Формула метрики (концептуально):
A11: ToxRaw = (2C + 2I + 2A) · Pot · Vec · Src · (1+Comp)
A12: ToxIndex = 100 · (ToxRaw - min(ToxRaw)) / (max(ToxRaw) - min(ToxRaw))
A14: Где:
A15: C,I,A — бинарные признаки нарушений конфиденциальности/целостности/доступности (0/1).
... A21: Примечание: веса можно менять (например, для КИИ усилить A и сетевой вектор). Это делается заменой коэффициентов в листе '2_Фичи'.
