Workbook

Sheet Опорный каркас киберугроз 2026
A1: № | B1: Официальное название | C1: Сленг специалиста информационной безопасности | D1: "Биологический" каркас | E1: Логика БХК (Тип ошибки) | F1: Топологический инвариант | G1: Уровень токсичности | H1: Время простоя МСП, час | I1: Время восстановления функциональности МСП, час | J1: Процент % потери производительной функциональности | K1: Время восстановления потерянных документов и отчетов, час | L1: Стоимость восстановления документов, руб. | M1: ИТОГО ущерб экономический
A2: 1 | B2: Deepfake-атаки | C2: Дипфейк-развод / подмена голоса и лица | D2: Мимикрия (мимикрия вида) | E2: Подмена конструкта личности | F2: Изоморфизм ложного и истинного профиля | G2: Критический | H2: 10 | I2: 48 | J2: 90 | K2: 16 | L2: =K2*$F$23*0.25 -> 2187500 | M2: =H23+I23+J23+L2 -> 36093750
A3: 2 | B3: Token Theft (Session Hijacking) | C3: Угон токена / кража сессии | D3: Кража рецептора | E3: Нарушение типизации сессии | F3: Разрыв связности «Владелец — Доступ» | G3: Критический | H3: 16 | I3: 40 | J3: 75 | K3: 24 | L3: =K3*$F$23*0.25 -> 3281250 | M3: =H23+I23+J23+L3 -> 37187500
A4: 3 | B4: LLM Jailbreaking | C4: Взлом промпта / джейлбрейк модели | D4: Гормональный сбой | E4: Логический парадокс в ядре | F4: Инверсия векторов управления | G4: Высокий | H4: 4 | I4: 16 | J4: 35 | K4: 48 | L4: =K4*$F$23*0.25 -> 6562500 | M4: =H23+I23+J23+L4 -> 40468750
A5: 4 | B5: Data Poisoning | C5: Отравление данных / poisoning датасета | D5: Генетическая мутация | E5: Ошибка в индуктивном выводе | F5: Деформация обучающего пространства | G5: Высокий | H5: 144 | I5: 480 | J5: 55 | K5: 360 | L5: =K5*$F$23*0.25 -> 49218750 | M5: =H23+I23+J23+L5 -> 83125000
A6: 5 | B6: Supply Chain Hijacking | C6: Взлом цепочки поставки / supply-chain захват | D6: Аутоиммунное поражение | E6: Нарушение транзитивности доверия | F6: Замкнутый цикл в графе поставок | G6: Критический | H6: 96 | I6: 336 | J6: 90 | K6: 480 | L6: =K6*$F$23*0.25 -> 65625000 | M6: =H23+I23+J23+L6 -> 99531250
A7: 6 | B7: Polymorphic Ransomware | C7: Полиморфный шифровальщик | D7: Вирус с изменчивым капсидом | E7: Неразрешимость алгоритма (P≠NP) | F7: Динамическая трансформация формы | G7: Высокий | H7: 192 | I7: 480 | J7: 95 | K7: 576 | L7: =K7*$F$23*0.25 -> 78750000 | M7: =H23+I23+J23+L7 -> 112656250
A8: 7 | B8: Triple Extortion | C8: Тройное вымогательство | D8: Полиорганная недостаточность | E8: Композиция (умножение) угроз | F8: Расширение границы поражения | G8: Критический | H8: 240 | I8: 576 | J8: 98 | K8: 720 | L8: =K8*$F$23*0.25 -> 98437500 | M8: =H23+I23+J23+L8 -> 132343750
A9: 8 | B9: Automated Botnet Swarms | C9: Ботнет-рой / swarm-атака | D9: Рой (групповой разум) | E9: Ошибка распределенного консенсуса | F9: Изменение глобальной связности сети | G9: Высокий | H9: 8 | I9: 48 | J9: 60 | K9: 72 | L9: =K9*$F$23*0.25 -> 9843750 | M9: =H23+I23+J23+L9 -> 43750000
A10: 9 | B10: Quantum-Decryption | C10: Квантовый взлом шифрования / post-quantum риск | D10: Разрушитель иммунитета | E10: Коллапс сложности доказательства | F10: Схлопывание криптографических дыр | G10: Критический | H10: 8760 | I10: 8760 | J10: 100 | K10: 8760 | L10: =K10*$F$23*0.25 -> 1197656250 | M10: =H23+I23+J23+L10 -> 1231562500
A11: 10 | B11: Ghost Logging | C11: Тихое логирование / невидимый сбор логов | D11: Невидимость (стелс) | E11: Доказательство «пустого» события | F11: Удаление ребер в графе аудита | G11: Средний | H11: 0 | I11: 480 | J11: 10 | K11: 480 | L11: =K11*$F$23*0.25 -> 65625000 | M11: =H23+I23+J23+L11 -> 99531250
A12: 11 | B12: API & Shadow AI Attacks | C12: Атаки на API и теневой ИИ | D12: Уязвимость мембраны | E12: Нарушение интерфейса типов | F12: Прокол в топологической границе | G12: Высокий | H12: 16 | I12: 72 | J12: 70 | K12: 120 | L12: =K12*$F$23*0.25 -> 16406250 | M12: =H23+I23+J23+L12 -> 50312500
A13: 12 | B13: Adaptive Malware | C13: Мутирующий вредонос / обход EDR | D13: Эволюционная адаптация | E13: Самодоказывающийся код | F13: Гомеоморфизм вредоносных функций | G13: Высокий | H13: 96 | I13: 336 | J13: 80 | K13: 480 | L13: =K13*$F$23*0.25 -> 65625000 | M13: =H23+I23+J23+L13 -> 99531250
A14: 13 | B14: Hyper-Phishing | C14: Гиперфишинг / AI-фишинг под человека | D14: Психосоматика | E14: Эксплуатация контекста | F14: Направленный граф «Доверие — Клик» | G14: Средний | H14: 2 | I14: 8 | J14: 30 | K14: 16 | L14: =K14*$F$23*0.25 -> 2187500 | M14: =H23+I23+J23+L14 -> 36093750
A15: 14 | B15: Cryptojacking 2.0 | C15: Скрытый майнинг 2.0 / криптоджекинг | D15: Паразитарный симбиоз | E15: Побочный эффект вычисления | F15: Скрытый цикл потребления ресурсов | G15: Средний | H15: 4 | I15: 24 | J15: 25 | K15: 32 | L15: =K15*$F$23*0.25 -> 4375000 | M15: =H23+I23+J23+L15 -> 38281250
A16: 15 | B16: Open Source Poisoning | C16: Отравление open-source пакетов | D16: Горизонтальный перенос генов | E16: Ошибка в библиотечных термах | F16: Внедрение подграфа в корень системы | G16: Высокий | H16: 240 | I16: 960 | J16: 65 | K16: 1440 | L16: =K16*$F$23*0.25 -> 196875000 | M16: =H23+I23+J23+L16 -> 230781250
A17: 16 | B17: Атаки на КИИ (Саботаж) | C17: Саботаж КИИ / удар по критике | D17: Инфаркт инфраструктуры | E17: Нарушение терминального состояния | F17: Полный разрыв графа жизнеобеспечения | G17: Критический | H17: 168 | I17: 720 | J17: 97 | K17: 960 | L17: =K17*$F$23*0.25 -> 131250000 | M17: =H23+I23+J23+L17 -> 165156250
F19: выручка в год | G19: выручка в день
E20: ООО "Серконс" | F20: 1400000000
E21: рабочих дней в год | F21: 320 | G21: =F20/F21 -> 4375000 | H21: экономические потери (потеря выручки)
E22: часов в день | F22: 8
E23: выручка в час | F23: =F20/F21/F22 -> 546875 | H23: =F23*H3 -> 8750000 | I23: =F23*I3 -> 21875000 | J23: =(G21*J3/100) -> 3281250
E24: курс рубля | F24: 78
F25: =F23/F24 -> 7011.2179 | G25: =G21/F24 -> 56089.744 | H25: =H23/F24 -> 112179.49 | I25: =I23/F24 -> 280448.72 | J25: =J23/F24 -> 42067.308

Sheet Параметры_года
A1: Параметры расчёта ущерба от простоя и бюджета ИБ по годам
A3: Год | B3: Выручка в год, руб. | C3: Маржинальная ценность дня, руб. | D3: Базовая стоимость восстановления в день, руб. | E3: Коэф. деградации | F3: Коэф. штрафов/репутации | G3: Средняя эффективность мер ИБ | H3: Комментарий | I3: Источник статистики/оценки | J3: URL
A4: 2024 | B4: 365000000 | C4: 500000 | D4: 250000 | E4: 0.45 | F4: 0.12 | G4: 0.32 | H4: Иллюстративный сценарий; пользователь меняет под свою фирму | I4: NIST/IBM/Sophos/Veeam + внутренняя отчётность | J4: https://nvlpubs.nist.gov/nistpubs/SpecialPublications/NIST.SP.800-55v1.pdf
A5: 2025 | B5: 401500000 | C5: 550000 | D5: 275000 | E5: 0.46 | F5: 0.13 | G5: 0.35 | H5: Рост цифровой зависимости и удорожание восстановления | I5: IBM / ENISA / Verizon | J5: https://www.ibm.com/think/insights/whats-new-2024-cost-of-a-data-breach-report
A6: 2026 | B6: 441650000 | C6: 605000 | D6: 302500 | E6: 0.48 | F6: 0.14 | G6: 0.38 | H6: Иллюстративный прогноз при росте сложности угроз | I6: ENISA / Sophos / Verizon | J6: https://www.enisa.europa.eu/publications/enisa-threat-landscape-2024

Sheet Угрозы_модель
A1: Модель ущерба от простоя, деструкции и восстановления по угрозам
A3: Год | B3: № | C3: Официальное название | D3: Биологический каркас | E3: Тип ошибки | F3: Инвариант | G3: Токсичность | H3: q_i,t вероятность | I3: k_crit | J3: T_down, дни | K3: T_degr, дни | L3: T_rec, дни | M3: L_irr, руб. | N3: C_down/day | O3: C_degr/day | P3: C_rec/day | Q3: L_i,t до мер | R3: m_i,t эффект мер | S3: L_i,t после мер | T3: ΔU_i,t предотвращено | U3: B_i,t вклад в бюджет | V3: Примечание
A4: 2024 | B4: 1 | C4: Deepfake-атаки | D4: Мимикрия (мимикрия вида) | E4: Подмена конструкта личности | F4: Изоморфизм ложного и истинного профиля | G4: Критический | H4: 0.18 | I4: 1 | J4: 5 | K4: 8 | L4: 18 | M4: 3500000 | N4: =VLOOKUP(A4,Параметры_года!$A$4:$J$6,3,FALSE())*I4 -> 500000 | O4: =N4*VLOOKUP(A4,Параметры_года!$A$4:$J$6,5,FALSE()) -> 225000 | P4: =VLOOKUP(A4,Параметры_года!$A$4:$J$6,4,FALSE()) -> 250000 | Q4: =(N4*J4)+(O4*K4)+(P4*L4)+M4 -> 12300000 | R4: =VLOOKUP(A4,Параметры_года!$A$4:$J$6,7,FALSE()) -> 0.32 | S4: =Q4*(1-R4) -> 8364000 | T4: =Q4-S4 -> 3936000 | U4: =H4*T4 -> 708480 | V4: Редактируемые входы: H:M; формулы: N:U
A5: 2024 | B5: 2 | C5: Token Theft (Session Hijacking) | D5: Кража рецептора | E5: Нарушение типизации сессии | F5: Разрыв связности «Владелец — Доступ» | G5: Критический | H5: 0.18 | I5: 1 | J5: 5 | K5: 8 | L5: 18 | M5: 3500000 | N5: =VLOOKUP(A5,Параметры_года!$A$4:$J$6,3,FALSE())*I5 -> 500000 | O5: =N5*VLOOKUP(A5,Параметры_года!$A$4:$J$6,5,FALSE()) -> 225000 | P5: =VLOOKUP(A5,Параметры_года!$A$4:$J$6,4,FALSE()) -> 250000 | Q5: =(N5*J5)+(O5*K5)+(P5*L5)+M5 -> 12300000 | R5: =VLOOKUP(A5,Параметры_года!$A$4:$J$6,7,FALSE()) -> 0.32 | S5: =Q5*(1-R5) -> 8364000 | T5: =Q5-S5 -> 3936000 | U5: =H5*T5 -> 708480 | V5: Редактируемые входы: H:M; формулы: N:U
A6: 2024 | B6: 3 | C6: LLM Jailbreaking | D6: Гормональный сбой | E6: Логический парадокс в ядре | F6: Инверсия векторов управления | G6: Высокий | H6: 0.12 | I6: 0.8 | J6: 3.5 | K6: 5 | L6: 12 | M6: 1750000 | N6: =VLOOKUP(A6,Параметры_года!$A$4:$J$6,3,FALSE())*I6 -> 400000 | O6: =N6*VLOOKUP(A6,Параметры_года!$A$4:$J$6,5,FALSE()) -> 180000 | P6: =VLOOKUP(A6,Параметры_года!$A$4:$J$6,4,FALSE()) -> 250000 | Q6: =(N6*J6)+(O6*K6)+(P6*L6)+M6 -> 7050000 | R6: =VLOOKUP(A6,Параметры_года!$A$4:$J$6,7,FALSE()) -> 0.32 | S6: =Q6*(1-R6) -> 4794000 | T6: =Q6-S6 -> 2256000 | U6: =H6*T6 -> 270720 | V6: Редактируемые входы: H:M; формулы: N:U
A7: 2024 | B7: 4 | C7: Data Poisoning | D7: Генетическая мутация | E7: Ошибка в индуктивном выводе | F7: Деформация обучающего пространства | G7: Высокий | H7: 0.12 | I7: 0.8 | J7: 3.5 | K7: 5 | L7: 12 | M7: 1750000 | N7: =VLOOKUP(A7,Параметры_года!$A$4:$J$6,3,FALSE())*I7 -> 400000 | O7: =N7*VLOOKUP(A7,Параметры_года!$A$4:$J$6,5,FALSE()) -> 180000 | P7: =VLOOKUP(A7,Параметры_года!$A$4:$J$6,4,FALSE()) -> 250000 | Q7: =(N7*J7)+(O7*K7)+(P7*L7)+M7 -> 7050000 | R7: =VLOOKUP(A7,Параметры_года!$A$4:$J$6,7,FALSE()) -> 0.32 | S7: =Q7*(1-R7) -> 4794000 | T7: =Q7-S7 -> 2256000 | U7: =H7*T7 -> 270720 | V7: Редактируемые входы: H:M; формулы: N:U
A8: 2024 | B8: 5 | C8: Supply Chain Hijacking | D8: Аутоиммунное поражение | E8: Нарушение транзитивности доверия | F8: Замкнутый цикл в графе поставок | G8: Критический | H8: 0.18 | I8: 1 | J8: 5 | K8: 8 | L8: 18 | M8: 3500000 | N8: =VLOOKUP(A8,Параметры_года!$A$4:$J$6,3,FALSE())*I8 -> 500000 | O8: =N8*VLOOKUP(A8,Параметры_года!$A$4:$J$6,5,FALSE()) -> 225000 | P8: =VLOOKUP(A8,Параметры_года!$A$4:$J$6,4,FALSE()) -> 250000 | Q8: =(N8*J8)+(O8*K8)+(P8*L8)+M8 -> 12300000 | R8: =VLOOKUP(A8,Параметры_года!$A$4:$J$6,7,FALSE()) -> 0.32 | S8: =Q8*(1-R8) -> 8364000 | T8: =Q8-S8 -> 3936000 | U8: =H8*T8 -> 708480 | V8: Редактируемые входы: H:M; формулы: N:U
A9: 2024 | B9: 6 | C9: Polymorphic Ransomware | D9: Вирус с изменчивым капсидом | E9: Неразрешимость алгоритма (P≠NP) | F9: Динамическая трансформация формы | G9: Высокий | H9: 0.12 | I9: 0.8 | J9: 3.5 | K9: 5 | L9: 12 | M9: 1750000 | N9: =VLOOKUP(A9,Параметры_года!$A$4:$J$6,3,FALSE())*I9 -> 400000 | O9: =N9*VLOOKUP(A9,Параметры_года!$A$4:$J$6,5,FALSE()) -> 180000 | P9: =VLOOKUP(A9,Параметры_года!$A$4:$J$6,4,FALSE()) -> 250000 | Q9: =(N9*J9)+(O9*K9)+(P9*L9)+M9 -> 7050000 | R9: =VLOOKUP(A9,Параметры_года!$A$4:$J$6,7,FALSE()) -> 0.32 | S9: =Q9*(1-R9) -> 4794000 | T9: =Q9-S9 -> 2256000 | U9: =H9*T9 -> 270720 | V9: Редактируемые входы: H:M; формулы: N:U
A10: 2024 | B10: 7 | C10: Triple Extortion | D10: Полиорганная недостаточность | E10: Композиция (умножение) угроз | F10: Расширение границы поражения | G10: Критический | H10: 0.18 | I10: 1 | J10: 5 | K10: 8 | L10: 18 | M10: 3500000 | N10: =VLOOKUP(A10,Параметры_года!$A$4:$J$6,3,FALSE())*I10 -> 500000 | O10: =N10*VLOOKUP(A10,Параметры_года!$A$4:$J$6,5,FALSE()) -> 225000 | P10: =VLOOKUP(A10,Параметры_года!$A$4:$J$6,4,FALSE()) -> 250000 | Q10: =(N10*J10)+(O10*K10)+(P10*L10)+M10 -> 12300000 | R10: =VLOOKUP(A10,Параметры_года!$A$4:$J$6,7,FALSE()) -> 0.32 | S10: =Q10*(1-R10) -> 8364000 | T10: =Q10-S10 -> 3936000 | U10: =H10*T10 -> 708480 | V10: Редактируемые входы: H:M; формулы: N:U
A11: 2024 | B11: 8 | C11: Automated Botnet Swarms | D11: Рой (групповой разум) | E11: Ошибка распределенного консенсуса | F11: Изменение глобальной связности сети | G11: Высокий | H11: 0.12 | I11: 0.8 | J11: 3.5 | K11: 5 | L11: 12 | M11: 1750000 | N11: =VLOOKUP(A11,Параметры_года!$A$4:$J$6,3,FALSE())*I11 -> 400000 | O11: =N11*VLOOKUP(A11,Параметры_года!$A$4:$J$6,5,FALSE()) -> 180000 | P11: =VLOOKUP(A11,Параметры_года!$A$4:$J$6,4,FALSE()) -> 250000 | Q11: =(N11*J11)+(O11*K11)+(P11*L11)+M11 -> 7050000 | R11: =VLOOKUP(A11,Параметры_года!$A$4:$J$6,7,FALSE()) -> 0.32 | S11: =Q11*(1-R11) -> 4794000 | T11: =Q11-S11 -> 2256000 | U11: =H11*T11 -> 270720 | V11: Редактируемые входы: H:M; формулы: N:U
A12: 2024 | B12: 9 | C12: Quantum-Decryption | D12: Разрушитель иммунитета | E12: Коллапс сложности доказательства | F12: Схлопывание криптографических дыр | G12: Критический | H12: 0.18 | I12: 1 | J12: 5 | K12: 8 | L12: 18 | M12: 3500000 | N12: =VLOOKUP(A12,Параметры_года!$A$4:$J$6,3,FALSE())*I12 -> 500000 | O12: =N12*VLOOKUP(A12,Параметры_года!$A$4:$J$6,5,FALSE()) -> 225000 | P12: =VLOOKUP(A12,Параметры_года!$A$4:$J$6,4,FALSE()) -> 250000 | Q12: =(N12*J12)+(O12*K12)+(P12*L12)+M12 -> 12300000 | R12: =VLOOKUP(A12,Параметры_года!$A$4:$J$6,7,FALSE()) -> 0.32 | S12: =Q12*(1-R12) -> 8364000 | T12: =Q12-S12 -> 3936000 | U12: =H12*T12 -> 708480 | V12: Редактируемые входы: H:M; формулы: N:U
A13: 2024 | B13: 10 | C13: Ghost Logging | D13: Невидимость (стелс) | E13: Доказательство «пустого» события | F13: Удаление ребер в графе аудита | G13: Средний | H13: 0.07 | I13: 0.6 | J13: 2 | K13: 3 | L13: 7 | M13: 750000 | N13: =VLOOKUP(A13,Параметры_года!$A$4:$J$6,3,FALSE())*I13 -> 300000 | O13: =N13*VLOOKUP(A13,Параметры_года!$A$4:$J$6,5,FALSE()) -> 135000 | P13: =VLOOKUP(A13,Параметры_года!$A$4:$J$6,4,FALSE()) -> 250000 | Q13: =(N13*J13)+(O13*K13)+(P13*L13)+M13 -> 3505000 | R13: =VLOOKUP(A13,Параметры_года!$A$4:$J$6,7,FALSE()) -> 0.32 | S13: =Q13*(1-R13) -> 2383400 | T13: =Q13-S13 -> 1121600 | U13: =H13*T13 -> 78512 | V13: Редактируемые входы: H:M; формулы: N:U
A14: 2024 | B14: 11 | C14: API & Shadow AI Attacks | D14: Уязвимость мембраны | E14: Нарушение интерфейса типов | F14: Прокол в топологической границе | G14: Высокий | H14: 0.12 | I14: 0.8 | J14: 3.5 | K14: 5 | L14: 12 | M14: 1750000 | N14: =VLOOKUP(A14,Параметры_года!$A$4:$J$6,3,FALSE())*I14 -> 400000 | O14: =N14*VLOOKUP(A14,Параметры_года!$A$4:$J$6,5,FALSE()) -> 180000 | P14: =VLOOKUP(A14,Параметры_года!$A$4:$J$6,4,FALSE()) -> 250000 | Q14: =(N14*J14)+(O14*K14)+(P14*L14)+M14 -> 7050000 | R14: =VLOOKUP(A14,Параметры_года!$A$4:$J$6,7,FALSE()) -> 0.32 | S14: =Q14*(1-R14) -> 4794000 | T14: =Q14-S14 -> 2256000 | U14: =H14*T14 -> 270720 | V14: Редактируемые входы: H:M; формулы: N:U
A15: 2024 | B15: 12 | C15: Adaptive Malware | D15: Эволюционная адаптация | E15: Самодоказывающийся код | F15: Гомеоморфизм вредоносных функций | G15: Высокий | H15: 0.12 | I15: 0.8 | J15: 3.5 | K15: 5 | L15: 12 | M15: 1750000 | N15: =VLOOKUP(A15,Параметры_года!$A$4:$J$6,3,FALSE())*I15 -> 400000 | O15: =N15*VLOOKUP(A15,Параметры_года!$A$4:$J$6,5,FALSE()) -> 180000 | P15: =VLOOKUP(A15,Параметры_года!$A$4:$J$6,4,FALSE()) -> 250000 | Q15: =(N15*J15)+(O15*K15)+(P15*L15)+M15 -> 7050000 | R15: =VLOOKUP(A15,Параметры_года!$A$4:$J$6,7,FALSE()) -> 0.32 | S15: =Q15*(1-R15) -> 4794000 | T15: =Q15-S15 -> 2256000 | U15: =H15*T15 -> 270720 | V15: Редактируемые входы: H:M; формулы: N:U
... A35: 2025 | B35: 16 | C35: Атаки на КИИ (Саботаж) | D35: Инфаркт инфраструктуры | E35: Нарушение терминального состояния | F35: Полный разрыв графа жизнеобеспечения | G35: Критический | H35: 0.1944 | I35: 1 | J35: 5.4 | K35: 8.64 | L35: 19.44 | M35: 3780000 | N35: =VLOOKUP(A35,Параметры_года!$A$4:$J$6,3,FALSE())*I35 -> 550000 | O35: =N35*VLOOKUP(A35,Параметры_года!$A$4:$J$6,5,FALSE()) -> 253000 | P35: =VLOOKUP(A35,Параметры_года!$A$4:$J$6,4,FALSE()) -> 275000 | Q35: =(N35*J35)+(O35*K35)+(P35*L35)+M35 -> 14281920 | R35: =VLOOKUP(A35,Параметры_года!$A$4:$J$6,7,FALSE()) -> 0.35 | S35: =Q35*(1-R35) -> 9283248 | T35: =Q35-S35 -> 4998672 | U35: =H35*T35 -> 971741.84 | V35: Редактируемые входы: H:M; формулы: N:U

Sheet Итог_по_году
A1: Итог расчёта бюджета ИБ как функции предотвращаемого ущерба
A3: Год | B3: Ожидаемый ущерб до мер | C3: Ожидаемый ущерб после мер | D3: Предотвращаемый ущерб | E3: Рекомендуемый бюджет ИБ | F3: Выручка в год | G3: Бюджет / выручка | H3: Средняя эффективность мер | I3: Комментарий
A4: 2024 | B4: =SUMPRODUCT((Угрозы_модель!$A$4:$A$35=A4)*(Угрозы_модель!$H$4:$H$35)*(Угрозы_модель!$Q$4:$Q$35)) -> 19942050 | C4: =SUMPRODUCT((Угрозы_модель!$A$4:$A$35=A4)*(Угрозы_модель!$H$4:$H$35)*(Угрозы_модель!$S$4:$S$35)) -> 13560594 | D4: =B4-C4 -> 6381456 | E4: =SUMIF(Угрозы_модель!$A$4:$A$35,A4,Угрозы_модель!$U$4:$U$35) -> 6381456 | F4: =VLOOKUP(A4,Параметры_года!$A$4:$J$6,2,FALSE()) -> 365000000 | G4: =E4/F4 -> 0.017483441 | H4: =VLOOKUP(A4,Параметры_года!$A$4:$J$6,7,FALSE()) -> 0.32 | I4: Бюджет трактуется как денежное отражение статистически предотвращаемого ущерба
A5: 2025 | B5: =SUMPRODUCT((Угрозы_модель!$A$4:$A$35=A5)*(Угрозы_модель!$H$4:$H$35)*(Угрозы_модель!$Q$4:$Q$35)) -> 25035124 | C5: =SUMPRODUCT((Угрозы_модель!$A$4:$A$35=A5)*(Угрозы_модель!$H$4:$H$35)*(Угрозы_модель!$S$4:$S$35)) -> 16272831 | D5: =B5-C5 -> 8762293.5 | E5: =SUMIF(Угрозы_модель!$A$4:$A$35,A5,Угрозы_модель!$U$4:$U$35) -> 8762293.5 | F5: =VLOOKUP(A5,Параметры_года!$A$4:$J$6,2,FALSE()) -> 401500000 | G5: =E5/F5 -> 0.021823894 | H5: =VLOOKUP(A5,Параметры_года!$A$4:$J$6,7,FALSE()) -> 0.35 | I5: Бюджет трактуется как денежное отражение статистически предотвращаемого ущерба
A6: 2026 | B6: =SUMPRODUCT((Угрозы_модель!$A$4:$A$35=A6)*(Угрозы_модель!$H$4:$H$35)*(Угрозы_модель!$Q$4:$Q$35)) -> 0 | C6: =SUMPRODUCT((Угрозы_модель!$A$4:$A$35=A6)*(Угрозы_модель!$H$4:$H$35)*(Угрозы_модель!$S$4:$S$35)) -> 0 | D6: =B6-C6 -> 0 | E6: =SUMIF(Угрозы_модель!$A$4:$A$35,A6,Угрозы_модель!$U$4:$U$35) -> 0 | F6: =VLOOKUP(A6,Параметры_года!$A$4:$J$6,2,FALSE()) -> 441650000 | G6: =E6/F6 -> 0 | H6: =VLOOKUP(A6,Параметры_года!$A$4:$J$6,7,FALSE()) -> 0.38 | I6: Бюджет трактуется как денежное отражение статистически предотвращаемого ущерба
A8: Базовая формула | B8: B_t = Σ_i q_i,t × ΔU_i,t
A9: Развёрнутая формула | B9: ΔU_i,t = [C_down·T_down + C_degr·T_degr + C_rec·T_rec + L_irr] × m_i,t

Sheet Источники_HIJK
A1: № | B1: Угроза | C1: H (T_down, ч) | D1: I (T_rec, ч) | E1: J (%) | F1: K (T_doc, ч) | G1: Метод | H1: Рейтинг достоверности | I1: Источник / обоснование
A2: 1 | B2: Deepfake-атаки | C2: 10 | D2: 48 | E2: 90 | F2: 16 | G2: Эмпирический | H2: ★★★★ | I2: Right-Hand.AI 2025: downtime up to 7 days; Gartner May 2025: 62% org hit deepfake SE. Median H=10h.
A3: 2 | B3: Token Theft (Session Hijacking) | C3: 16 | D3: 40 | E3: 75 | F3: 24 | G3: Эмпирический | H3: ★★★★ | I3: IBM X-Force 2024: stolen creds 30% incidents; CSA 2024: 73% hijacking → cloud; Cisco Talos 2024: 60% IR = identity vector. Verizon DBIR 2025.
A4: 3 | B4: LLM Jailbreaking | C4: 4 | D4: 16 | E4: 35 | F4: 48 | G4: Дельфи/κ_obs | H4: ★★☆☆ | I4: OWASP LLM Top-10 2025 (LLM03); IBM CODB 2025: 31% AI breaches = operational disruption. No direct T_down data — Delphi κ_obs=0.6.
A5: 4 | B5: Data Poisoning | C5: 144 | D5: 480 | E5: 55 | F5: 360 | G5: Эмпирический | H5: ★★★★ | I5: Wiz 2025: full dataset rollback required; Obsidian 2025: MTTR; IBM CODB 2025: AI incident avg $4.5M + disruption. Data Poisoning recovery weeks.
A6: 5 | B6: Supply Chain Hijacking | C6: 96 | D6: 336 | E6: 90 | F6: 480 | G6: Эмпирический | H6: ★★★★ | I6: SOCRadar 2025: 72% orgs >1 week recovery; TechRadar: manufacturing/healthcare >6 wk; IBM CODB: supply chain breach $4.91M avg.
A7: 6 | B7: Polymorphic Ransomware | C7: 192 | D7: 480 | E7: 95 | F7: 576 | G7: Эмпирический | H7: ★★★★ | I7: Huntress 2026: avg ransomware downtime 24 days; Sophos 2025: avg recovery $1.53M; Coveware Q4 2024: encryption <4h; Halcyon: 21 days avg.
A8: 7 | B8: Triple Extortion | C8: 240 | D8: 576 | E8: 98 | F8: 720 | G8: Эмпирический | H8: ★★★★ | I8: Verizon DBIR 2025: ransomware 44% breaches; Halcyon 2025: 77% incidents = exfil before encrypt; IBM: $5.08M avg ransomware breach.
A9: 8 | B9: Automated Botnet Swarms | C9: 8 | D9: 48 | E9: 60 | F9: 72 | G9: Эмпирический | H9: ★★★★ | I9: DBIR 2025: SMB DDoS/botnet pattern; Cloudflare 2025: US 14.3% global DDoS. DDoS-only downtime typically <1 day for SMB without data loss.
A10: 9 | B10: Quantum-Decryption | C10: 8760 | D10: 8760 | E10: 100 | F10: 8760 | G10: Дельфи/κ_obs | H10: ★★☆☆ | I10: Thales 2025: 62% CNI orgs fear future encryption compromise. Harvest-now-decrypt-later. No realised T_down — Delphi extrapolation κ_obs=0.1.
A11: 10 | B11: Ghost Logging | C11: 0 | D11: 480 | E11: 10 | F11: 480 | G11: Дельфи/κ_obs | H11: ★★☆☆ | I11: IBM CODB 2025: median detection 204 days; Ghost Logging = zero visible T_down, latent damage. Delphi κ_obs=0.3. J reflects background degradation.
A12: 11 | B12: API & Shadow AI Attacks | C12: 16 | D12: 72 | E12: 70 | F12: 120 | G12: Эмпирический | H12: ★★★★ | I12: IBM CODB 2025: shadow AI breach +$670K; 1 in 5 orgs breached via shadow AI; SaaS breaches +300% (Sep2023–2024). Cisco Talos 2024.
A13: 12 | B13: Adaptive Malware | C13: 96 | D13: 336 | E13: 80 | F13: 480 | G13: Эмпирический | H13: ★★★★ | I13: Sophos 2025: avg recovery $1.53M; ENISA TL 2025: adaptive malware evades EDR; Huntress 2026: full domain encryption <4h, recovery 24 days.
... A17: 16 | B17: Атаки на КИИ (Саботаж) | C17: 168 | D17: 720 | E17: 97 | F17: 960 | G17: Эмпирический | H17: ★★★★ | I17: FBI IC3 2025: CNI primary ransomware target; London hospitals 2024: >800 ops cancelled; Change Healthcare 2024: weeks offline; manufacturing avg 72h (StationX 2026).
A20: ЛЕГЕНДА:
A21: Эмпирический (синий) | B21: ★★★★ — данные из Verizon DBIR, IBM CODB, Sophos, Huntress, SOCRadar (2024–2025)
A22: Дельфи/κ_obs (зелёный) | B22: ★★☆☆ — κ_obs < 0.7; требует экспертной панели n≥12, CR < 0.10 (Dalkey & Helmer 1963)
A23: Экстраполяция (жёлтый) | B23: ★☆☆☆ — угроза формирующаяся; BAI-экстраполяция по NTI (формула 7, Статья 3)
